{"Bkav": null, "DrWeb": "modification of W97M.Suspicious.1", "MicroWorld-eScan": "W97M.Downloader.CWW", "CMC": null, "CAT-QuickHeal": "X97M.Downloader.5034", "McAfee": null, "Malwarebytes": null, "Zillya": null, "Sangfor": "Malware", "K7AntiVirus": null, "K7GW": null, "Arcabit": "HEUR.VBA.CG.2", "BitDefenderTheta": null, "F-Prot": "X97M/Downldr.Q.gen", "Symantec": "ISB.Downloader!gen77", "ESET-NOD32": "VBA/TrojanDownloader.Agent.CFF", "TrendMicro-HouseCall": "W2KM_PSWMILOAD.SM1", "Avast": "MO97:Downloader-WT [Trj]", "ClamAV": "Doc.Dropper.Donoff-5743532-0", "Kaspersky": "HEUR:Trojan-Downloader.Script.Generic", "BitDefender": "W97M.Downloader.CWW", "NANO-Antivirus": "Trojan.Script.Agent.eqaezi", "ViRobot": null, "SUPERAntiSpyware": null, "Tencent": "HEUR:RiskWare.Vba.Generic.a", "Ad-Aware": "W97M.Downloader.CWW", "Sophos": "Troj/Morgan-CE", "Comodo": "TrojWare.VBS.TrojanDownloader.Agent.CFF@8g5yid", "F-Secure": "Trojan:W97M/MaliciousMacro.GEN", "Baidu": "VBA.Trojan-Downloader.Agent.cdp", "VIPRE": null, "TrendMicro": "W2KM_PSWMILOAD.SM1", "McAfee-GW-Edition": "BehavesLike.Downloader.nr", "FireEye": "W97M.Downloader.CWW", "Emsisoft": "W97M.Downloader.CWW (B)", "Ikarus": "Trojan-Downloader.PowerShell.Agent", "Cyren": "X97M/Downldr.Q.gen", "Jiangmin": null, "Antiy-AVL": null, "Kingsoft": null, "Microsoft": "Trojan:PowerShell/Casur.CS!eml", "Endgame": "malicious (high confidence)", "AegisLab": null, "ZoneAlarm": "HEUR:Trojan-Downloader.Script.Generic", "Avast-Mobile": null, "GData": "W97M.Downloader.CWW", "TACHYON": "Suspicious/X97M.Obfus.Gen.6", "AhnLab-V3": null, "VBA32": null, "ALYac": "W97M.Downloader.CWW", "MAX": "malware (ai score=83)", "Zoner": "Probably W97Shell", "Rising": "Heur.Macro.powershell.a (CLASSIC)", "Yandex": null, "SentinelOne": "DFI - Malicious OLE", "Fortinet": "WM/Agent.D73A!tr", "AVG": "MO97:Downloader-WT [Trj]", "Panda": null, "Qihoo-360": "heur.macro.powershell.2"}
