{"Bkav": null, "DrWeb": null, "MicroWorld-eScan": "W97M.Dropper.FN", "CMC": null, "CAT-QuickHeal": "W97M.Downloader.EP", "McAfee": "W97M/Dropper.bm", "Malwarebytes": null, "VIPRE": "LooksLike.Macro.Malware.n (v)", "K7AntiVirus": null, "K7GW": null, "Arcabit": "HEUR.VBA.CG.1", "BitDefenderTheta": null, "F-Prot": "W97M/Dropper.gen", "Symantec": "Trojan.Gen.MBT", "TotalDefense": null, "TrendMicro-HouseCall": "W2KM_HANCITOR.QFA", "Avast": "VBA:Downloader-CIM [Trj]", "ClamAV": "Doc.Downloader.Generic-6698422-0", "Kaspersky": "HEUR:Trojan.Script.Agent.gen", "BitDefender": "W97M.Dropper.FN", "NANO-Antivirus": "Trojan.Script.Inject.eeenfm", "SUPERAntiSpyware": null, "Tencent": "Heur.Macro.Generic.Gen.a", "Ad-Aware": "W97M.Dropper.FN", "Emsisoft": "W97M.Dropper.FN (B)", "Comodo": null, "F-Secure": "Trojan-Dropper:W97M/Fareit.H", "Baidu": "VBA.Trojan-Dropper.Agent.kc", "Zillya": null, "TrendMicro": "W2KM_HANCITOR.QFA", "McAfee-GW-Edition": "BehavesLike.Downloader.db", "Fortinet": "WM/TrojanDropper.LG!tr", "FireEye": "W97M.Dropper.FN", "Sophos": "Troj/DocDl-DTN", "Ikarus": "Trojan-Dropper.VBA.Agent", "Cyren": "W97M/Dropper.gen", "Jiangmin": null, "Avira": "W2000M/Dldr.Agent.AM.29880", "MAX": "malware (ai score=80)", "Kingsoft": null, "Endgame": "malicious (high confidence)", "Microsoft": "TrojanDropper:O97M/Farheyt.C", "ViRobot": null, "ZoneAlarm": "HEUR:Trojan.Script.Agent.gen", "Avast-Mobile": null, "AhnLab-V3": "W97M/Dropper", "VBA32": null, "ALYac": "W97M.Dropper.FN", "TACHYON": null, "Zoner": "Probably W97Obfuscated", "ESET-NOD32": "VBA/TrojanDropper.Agent.LF", "Rising": "Dropper.Farheyt!8.1BD4 (TOPIS:E0:AXqUYeV9WwU)", "Yandex": null, "SentinelOne": "DFI - Malicious OLE", "MaxSecure": null, "GData": "W97M.Dropper.FN", "AVG": "VBA:Downloader-CIM [Trj]", "Panda": null, "Qihoo-360": "virus.office.obfuscated.1"}
