{"Bkav": null, "DrWeb": "Exploit.Siggen.42530", "MicroWorld-eScan": "VB:Trojan.VBA.Downloader.UK", "CMC": null, "CAT-QuickHeal": null, "McAfee": null, "Malwarebytes": null, "Zillya": null, "AegisLab": null, "K7AntiVirus": "Trojan ( 00536d111 )", "K7GW": "Trojan ( 00536d111 )", "Arcabit": "VB:Trojan.VBA.Downloader.UK", "BitDefenderTheta": null, "Cyren": null, "Symantec": null, "ESET-NOD32": "VBA/TrojanDownloader.Agent.QOA", "TrendMicro-HouseCall": "TROJ_FRS.VSNTKM19", "Avast": "SNH:Script [Dropper]", "ClamAV": null, "Kaspersky": "HEUR:Trojan-Downloader.MSOffice.SLoad.gen", "BitDefender": "VB:Trojan.VBA.Downloader.UK", "NANO-Antivirus": null, "SUPERAntiSpyware": null, "Tencent": null, "Ad-Aware": "VB:Trojan.VBA.Downloader.UK", "Sophos": "Troj/DocDl-WNT", "Comodo": null, "F-Secure": "Trojan:W97M/Nastjencro.A", "Baidu": null, "VIPRE": null, "TrendMicro": null, "McAfee-GW-Edition": "BehavesLike.Downloader.cg", "FireEye": "VB:Trojan.VBA.Downloader.UK", "Emsisoft": null, "SentinelOne": "DFI - Suspicious OLE", "F-Prot": null, "Jiangmin": null, "Avira": null, "Kingsoft": null, "Microsoft": "Trojan:Script/Casur.A!cl", "Endgame": "malicious (high confidence)", "ViRobot": null, "ZoneAlarm": "HEUR:Trojan-Downloader.MSOffice.SLoad.gen", "Avast-Mobile": null, "GData": "VB:Trojan.VBA.Downloader.UK", "AhnLab-V3": null, "VBA32": null, "ALYac": "VB:Trojan.VBA.Downloader.UK", "MAX": "malware (ai score=81)", "Zoner": "Probably W97DownloaderA", "Rising": "Downloader.Agent!8.B23 (TOPIS:E0:BvMgJNuQQBK)", "Yandex": null, "TACHYON": null, "MaxSecure": null, "Fortinet": "VBA/Agent.QOA!tr.dldr", "AVG": "SNH:Script [Dropper]", "Panda": null, "Qihoo-360": null}
