{"Bkav": null, "TotalDefense": null, "MicroWorld-eScan": null, "CMC": null, "CAT-QuickHeal": null, "ALYac": null, "Malwarebytes": null, "Zillya": null, "SUPERAntiSpyware": null, "Sangfor": null, "K7AntiVirus": null, "K7GW": null, "Arcabit": null, "Baidu": null, "F-Prot": null, "Symantec": null, "ESET-NOD32": null, "TrendMicro-HouseCall": null, "ClamAV": null, "Kaspersky": null, "BitDefender": null, "NANO-Antivirus": null, "ViRobot": null, "Rising": null, "Ad-Aware": null, "Emsisoft": null, "Comodo": null, "F-Secure": null, "DrWeb": null, "VIPRE": null, "TrendMicro": null, "McAfee-GW-Edition": null, "FireEye": null, "Sophos": null, "SentinelOne": null, "Cyren": null, "Jiangmin": null, "Avira": null, "Fortinet": null, "Antiy-AVL": null, "Kingsoft": null, "Endgame": null, "AegisLab": null, "ZoneAlarm": null, "Avast-Mobile": null, "TACHYON": null, "AhnLab-V3": null, "McAfee": null, "MAX": null, "VBA32": null, "Zoner": null, "Tencent": null, "Yandex": null, "Ikarus": null, "GData": null, "Panda": null, "Qihoo-360": null}
