{"Bkav": null, "DrWeb": "W97M.DownLoader.4191", "MicroWorld-eScan": "W97m.Downloader.IQU", "CMC": null, "CAT-QuickHeal": "W97M.Emotet.36302", "McAfee": "W97M/Downloader.xx", "Malwarebytes": null, "Zillya": null, "SUPERAntiSpyware": null, "Sangfor": null, "K7AntiVirus": null, "K7GW": null, "Arcabit": "W97m.Downloader.IQU", "BitDefenderTheta": null, "F-Prot": null, "Symantec": "W97M.Downloader", "TotalDefense": null, "TrendMicro-HouseCall": "Trojan.W97M.POWLOAD.EHT", "Avast": "Other:Malware-gen [Trj]", "ClamAV": "Doc.Downloader.Emotet-7400269-0", "Kaspersky": "HEUR:Trojan.MSOffice.SAgent.gen", "BitDefender": "W97m.Downloader.IQU", "NANO-Antivirus": "Trojan.Script.Downloader.ghylsa", "AegisLab": null, "Rising": null, "Endgame": "malicious (high confidence)", "Emsisoft": null, "Comodo": null, "F-Secure": "Heuristic.HEUR/Macro.Downloader.MRUK.Gen", "Baidu": null, "VIPRE": null, "McAfee-GW-Edition": "BehavesLike.Downloader.cl", "FireEye": "W97m.Downloader.IQU", "Sophos": "Mal/DocDl-K", "Cyren": "W97M/Downldr.HB.gen!Eldorado", "Jiangmin": null, "Avira": "HEUR/Macro.Downloader.MRUK.Gen", "Fortinet": "VBA/Agent.QLT!tr.dldr", "Kingsoft": null, "Microsoft": "TrojanDownloader:O97M/Emotet.GF!MTB", "ViRobot": null, "ZoneAlarm": "HEUR:Trojan.MSOffice.SAgent.gen", "Avast-Mobile": null, "TACHYON": "Suspicious/W97M.Obfus.Gen.8", "AhnLab-V3": "VBA/Downloader.S71", "ALYac": "W97m.Downloader.IQU", "MAX": "malware (ai score=88)", "VBA32": null, "Zoner": "Probably W97Obfuscated", "ESET-NOD32": "VBA/TrojanDownloader.Agent.QMI", "Tencent": "Heur.Macro.Generic.Gen.f", "Yandex": null, "SentinelOne": "DFI - Malicious OLE", "GData": "Macro.Trojan.Kryptik.NK@susp", "Ad-Aware": "W97m.Downloader.IQU", "AVG": "Other:Malware-gen [Trj]", "Panda": "O97M/Downloader", "Qihoo-360": "virus.office.obfuscated.1"}
