{"Bkav": null, "MicroWorld-eScan": "W97M.Downloader.IDF", "CMC": null, "CAT-QuickHeal": "W97M.Downloader.35623", "McAfee": "W97M/Downloader!B603ED0C18A3", "Malwarebytes": null, "Zillya": null, "SUPERAntiSpyware": null, "Sangfor": "Malware", "K7AntiVirus": "Trojan ( 0054eb301 )", "K7GW": "Trojan ( 0054eb301 )", "Arcabit": "HEUR.VBA.CG.2", "Baidu": null, "F-Prot": null, "Symantec": "W97M.Downloader", "ESET-NOD32": "VBA/TrojanDownloader.Agent.NZX", "TrendMicro-HouseCall": "Trojan.W97M.POWLOAD.TIHAOHDT", "Avast": null, "ClamAV": "Doc.Downloader.Generic-6972771-0", "Kaspersky": "HEUR:Trojan.Script.Generic", "BitDefender": "W97M.Downloader.IDF", "NANO-Antivirus": "Trojan.Script.ExpKit.fqovnu", "AegisLab": null, "Tencent": "Heur:Trojan.Script.LS_Gencirc.7137795.0", "Ad-Aware": "W97M.Downloader.IDF", "Emsisoft": "Trojan-Downloader.Macro.Generic.T (A)", "Comodo": null, "F-Secure": "Malware.W97M/Agent.6947551", "DrWeb": "W97M.DownLoader.4014", "VIPRE": null, "TrendMicro": "Trojan.W97M.POWLOAD.TIHAOHDT", "McAfee-GW-Edition": "BehavesLike.Downloader.cb", "Fortinet": "VBA/Agent.DF8D!tr.dldr", "FireEye": "W97M.Downloader.IDF", "Sophos": "Troj/DocDl-TTP", "SentinelOne": "DFI - Malicious OLE", "Cyren": "W97M/Downldr.BW.gen!Eldorado", "Jiangmin": "Trojan.MSOffice.SAgent.a", "Avira": "W97M/Agent.6947551", "MAX": "malware (ai score=87)", "Antiy-AVL": "Trojan[Downloader]/MSOffice.Agent.nzx", "Kingsoft": null, "Endgame": "malicious (high confidence)", "Microsoft": "TrojanDownloader:O97M/Obfuse.EV", "ViRobot": null, "AhnLab-V3": "VBA/Downloader.S15", "ZoneAlarm": "HEUR:Trojan.Script.Generic", "Avast-Mobile": null, "TotalDefense": null, "ALYac": "W97M.Downloader.IDF", "TACHYON": "Suspicious/W97M.Obfus.Gen.6", "VBA32": "Trojan-Downloader.O97M.Obfuse.EV", "Zoner": "Probably W97Obfuscated", "Rising": "Trojan.Runner/VBA!1.B869 (CLASSIC)", "Yandex": null, "Ikarus": "Trojan-Downloader.VBA.Agent", "MaxSecure": null, "GData": "Macro.Trojan-Downloader.Posh.Z@gen", "AVG": null, "Panda": null, "Qihoo-360": null}
