{"Bkav": null, "TotalDefense": null, "MicroWorld-eScan": "Trojan.GenericKDZ.60781", "FireEye": "Trojan.GenericKDZ.60781", "CAT-QuickHeal": null, "McAfee": null, "Malwarebytes": null, "Zillya": null, "SUPERAntiSpyware": null, "Sangfor": null, "Trustlook": null, "Alibaba": null, "K7GW": null, "K7AntiVirus": null, "Arcabit": "Trojan.Generic.DED6D", "Baidu": null, "F-Prot": null, "Symantec": null, "ESET-NOD32": "VBA/TrojanDownloader.Agent.QXU", "TrendMicro-HouseCall": null, "Avast": null, "ClamAV": "Doc.Downloader.Emotet-7388439-0", "Kaspersky": null, "BitDefender": "Trojan.GenericKDZ.60781", "NANO-Antivirus": null, "ViRobot": null, "Tencent": "Heur.Macro.Generic.Gen.h", "Ad-Aware": "Trojan.GenericKDZ.60781", "Emsisoft": "Trojan.GenericKDZ.60781 (B)", "Comodo": null, "F-Secure": "Heuristic.HEUR/Macro.Downloader.MRJI.Gen", "DrWeb": null, "VIPRE": null, "TrendMicro": null, "McAfee-GW-Edition": null, "Fortinet": "VBA/Agent.136E!tr.dldr", "CMC": null, "Sophos": "Mal/DocDl-K", "SentinelOne": "DFI - Malicious OPENXML", "Cyren": null, "Jiangmin": null, "Avira": "HEUR/Macro.Downloader.MRJI.Gen", "MAX": "malware (ai score=80)", "Antiy-AVL": null, "Kingsoft": null, "Endgame": "malicious (high confidence)", "Microsoft": "Trojan:Script/Casur.A!cl", "AegisLab": null, "ZoneAlarm": null, "Avast-Mobile": null, "AhnLab-V3": "VBA/Downloader.S94", "VBA32": null, "ALYac": null, "TACHYON": null, "Zoner": "Probably W97Obfuscated", "Rising": null, "Yandex": null, "Ikarus": null, "GData": "Trojan.GenericKDZ.60781", "AVG": null, "Panda": null, "Qihoo-360": "virus.office.qexvmc.1085"}
