{"Bkav": null, "TotalDefense": null, "MicroWorld-eScan": null, "CMC": null, "CAT-QuickHeal": "O97M.Dropper.AX", "McAfee": null, "Malwarebytes": null, "Zillya": null, "SUPERAntiSpyware": null, "Sangfor": "Malware", "K7AntiVirus": null, "K7GW": null, "Arcabit": "HEUR.VBA.CG.2", "BitDefenderTheta": null, "F-Prot": null, "Symantec": null, "ESET-NOD32": "PowerShell/TrojanDownloader.Agent.AP", "Baidu": "VBA.Trojan-Downloader.Agent.cme", "TrendMicro-HouseCall": "Mal_Powload-II", "Avast": "VBA:Downloader-DLC [Trj]", "Kaspersky": null, "BitDefender": null, "NANO-Antivirus": "Trojan.Ole2.Vbs-heuristic.druvzi", "ViRobot": null, "Tencent": "OLE.Win32.Macro.703744", "Ad-Aware": null, "Emsisoft": null, "Comodo": null, "F-Secure": "Heuristic.HEUR/Macro.Downloader.AMCV.Gen", "DrWeb": "modification of W97M.Suspicious.1", "VIPRE": null, "TrendMicro": "Mal_Powload-II", "McAfee-GW-Edition": "BehavesLike.Downloader.nl", "Fortinet": null, "FireEye": null, "Sophos": null, "SentinelOne": "DFI - Malicious OLE", "Cyren": null, "Jiangmin": "W97M/Niceday.o", "Avira": "HEUR/Macro.Downloader.AMCV.Gen", "MAX": null, "Antiy-AVL": null, "Kingsoft": null, "Endgame": "malicious (high confidence)", "Microsoft": "Trojan:O97M/Foretype.A!ml", "AegisLab": null, "ZoneAlarm": null, "Avast-Mobile": null, "AhnLab-V3": null, "ALYac": null, "TACHYON": null, "VBA32": null, "Zoner": "Probably W97Shell", "Rising": "Macro.Powershell.b (CLASSIC)", "Yandex": null, "Ikarus": null, "GData": null, "AVG": "VBA:Downloader-DLC [Trj]", "Panda": null, "Qihoo-360": "heur.macro.powershell.1"}
