{"Bkav": null, "MicroWorld-eScan": "VB.EmoDldr.6.Gen", "VBA32": null, "FireEye": "VB.EmoDldr.6.Gen", "CAT-QuickHeal": "O97M.Downloader.30507", "McAfee": "W97M/Downloader.gs", "Malwarebytes": null, "Zillya": null, "SUPERAntiSpyware": null, "Sangfor": "Malware", "K7AntiVirus": null, "K7GW": null, "Arcabit": "HEUR.VBA.A.1", "Baidu": null, "F-Prot": "XML/Agent.C", "Symantec": "W97M.Downloader", "TotalDefense": null, "TrendMicro-HouseCall": "Trojan.W97M.POWLOAD.SMRV02", "Avast": "VBA:Downloader-GEX [Trj]", "ClamAV": null, "Kaspersky": "HEUR:Trojan-Downloader.MSOffice.SLoad.gen", "BitDefender": "VB.EmoDldr.6.Gen", "NANO-Antivirus": "Trojan.Ole2.Vbs-heuristic.druvzi", "ViRobot": null, "Tencent": "Heur:Trojan.Script.LS_Gencirc.7111837.0", "Endgame": "malicious (high confidence)", "Sophos": null, "Comodo": null, "F-Secure": "Malware.W2000M/Agent.0143194", "DrWeb": "W97M.DownLoader.3053", "VIPRE": null, "TrendMicro": "Trojan.W97M.POWLOAD.SMRV02", "McAfee-GW-Edition": "BehavesLike.Downloader.nl", "CMC": null, "Emsisoft": "VB.EmoDldr.6.Gen (B)", "SentinelOne": "DFI - Malicious OLE", "Cyren": "XML/Agent.C", "Jiangmin": null, "Avira": "W2000M/Agent.0143194", "Fortinet": "VBA/Agent.RMY!tr.dldr", "Kingsoft": null, "Microsoft": "TrojanDownloader:O97M/Obfuse.CP", "AegisLab": null, "ZoneAlarm": "HEUR:Trojan-Downloader.MSOffice.SLoad.gen", "Avast-Mobile": null, "TACHYON": "Suspicious/X97M.Script.Gen", "AhnLab-V3": null, "BitDefenderTheta": null, "ALYac": "VB.EmoDldr.6.Gen", "MAX": "malware (ai score=83)", "Ad-Aware": "VB.EmoDldr.6.Gen", "Zoner": "Probably W97Shell", "ESET-NOD32": "VBA/TrojanDownloader.Agent.MFM", "Rising": "Downloader.Obfuse!8.105AD (TOPIS:E0:Kndnrz0J2MB)", "Yandex": null, "Ikarus": "Trojan.VBA.Agent", "MaxSecure": null, "GData": "VB.EmoDldr.6.Gen", "AVG": "VBA:Downloader-GEX [Trj]", "Panda": null, "Qihoo-360": "virus.office.qexvmc.1085"}
