{"Bkav": null, "DrWeb": null, "MicroWorld-eScan": null, "CMC": null, "CAT-QuickHeal": null, "McAfee": "W97M/Dropper.el", "Malwarebytes": null, "Zillya": null, "SUPERAntiSpyware": null, "Sangfor": null, "K7AntiVirus": null, "K7GW": null, "BitDefenderTheta": null, "F-Prot": null, "Symantec": null, "ESET-NOD32": "a variant of VBA/TrojanDropper.Agent.ANT", "TrendMicro-HouseCall": "Trojan.X97M.GRACEWIRE.D", "Avast": null, "ClamAV": null, "Kaspersky": "HEUR:Trojan-Dropper.MSOffice.SDrop.gen", "BitDefender": null, "NANO-Antivirus": null, "ViRobot": null, "Tencent": null, "Endgame": "malicious (high confidence)", "Emsisoft": null, "Comodo": null, "F-Secure": "Malware.X97M/Agent.396871082", "Baidu": null, "VIPRE": null, "TrendMicro": "Trojan.X97M.GRACEWIRE.D", "McAfee-GW-Edition": "BehavesLike.Dropper.tg", "FireEye": null, "Sophos": "Troj/DocDrp-QA", "SentinelOne": "DFI - Suspicious OLE", "Cyren": null, "Jiangmin": null, "Avira": "X97M/Agent.396871082", "Fortinet": "VBA/Agent.ANT!tr", "Kingsoft": null, "Arcabit": null, "AegisLab": null, "AhnLab-V3": "VBA/Loader.S3", "ZoneAlarm": "HEUR:Trojan-Dropper.MSOffice.SDrop.gen", "Avast-Mobile": null, "Microsoft": "TrojanDropper:O97M/GraceWire.N!MTB", "TACHYON": "Suspicious/W97.NS.Gen", "TotalDefense": null, "VBA32": null, "ALYac": null, "MAX": null, "Ad-Aware": null, "Zoner": null, "Rising": "Dropper.StealthLoader/VBA!1.BF03 (CLASSIC)", "Yandex": null, "Ikarus": null, "MaxSecure": null, "GData": "Macro.Trojan-Dropper.Agent.APK", "AVG": null, "Panda": null, "Qihoo-360": null}
