{"Bkav": null, "DrWeb": null, "MicroWorld-eScan": "W97M.Downloader.DYT", "CMC": null, "CAT-QuickHeal": "W97M.Downloader.GH", "McAfee": "W97M/Downloader.bkq", "Malwarebytes": null, "VIPRE": "LooksLike.Macro.Malware.n (v)", "K7AntiVirus": "Trojan ( 00536d111 )", "K7GW": "Trojan ( 00536d111 )", "Arcabit": "W97M.Downloader.DYT", "BitDefenderTheta": null, "F-Prot": "New or modified W97M/Downloader", "Symantec": "W97M.Downloader", "TotalDefense": null, "TrendMicro-HouseCall": "TROJ_FRS.0NA003GM16", "Avast": "VBA:Downloader-CMZ [Trj]", "ClamAV": "Doc.Malware.Chronos-6897935-0", "Kaspersky": "Trojan-Downloader.VBS.Agent.bwz", "BitDefender": "W97M.Downloader.DYT", "NANO-Antivirus": "Trojan.Ole2.Vbs-heuristic.druvzi", "SUPERAntiSpyware": null, "Tencent": null, "Ad-Aware": "W97M.Downloader.DYT", "Emsisoft": "W97M.Downloader.DYT (B)", "F-Secure": "Trojan:W97M/Nastjencro.A", "Baidu": "VBA.Trojan-Dropper.Agent.lm", "Zillya": null, "TrendMicro": "TROJ_FRS.0NA003GM16", "McAfee-GW-Edition": "BehavesLike.Dropper.cl", "Fortinet": "WM/Agent.MI!tr", "FireEye": "W97M.Downloader.DYT", "Sophos": "Troj/DocDl-EAC", "SentinelOne": null, "Cyren": "W97M/Downloader", "Jiangmin": null, "Avira": "W2000M/Agent.345745", "MAX": "malware (ai score=84)", "Kingsoft": null, "Endgame": "malicious (high confidence)", "Microsoft": "Trojan:O97M/Madeba.A!det", "ViRobot": null, "ZoneAlarm": "Trojan-Downloader.VBS.Agent.bwz", "Avast-Mobile": null, "AhnLab-V3": "W97M/Downloader", "VBA32": null, "ALYac": "W97M.Downloader.DYT", "TACHYON": null, "Zoner": null, "ESET-NOD32": null, "Rising": "Macro.Agent.et (CLASSIC)", "Yandex": null, "Ikarus": "Trojan-Downloader.VBA.Agent", "GData": "W97M.Downloader.DYT", "AVG": "VBA:Downloader-CMZ [Trj]", "Panda": "W97M/Downloader", "Qihoo-360": "virus.office.qexvmc.1085"}
