{"Bkav": null, "MicroWorld-eScan": null, "CMC": null, "CAT-QuickHeal": null, "ALYac": null, "Malwarebytes": null, "Zillya": null, "Sangfor": "Malware", "K7AntiVirus": null, "K7GW": null, "Arcabit": "HEUR.VBA.Trojan.d", "Baidu": null, "F-Prot": null, "ESET-NOD32": null, "TrendMicro-HouseCall": null, "Avast": null, "ClamAV": null, "Kaspersky": null, "BitDefender": null, "NANO-Antivirus": null, "ViRobot": null, "AegisLab": null, "Tencent": null, "Ad-Aware": null, "Sophos": null, "Comodo": null, "F-Secure": null, "DrWeb": null, "VIPRE": "LooksLike.Macro.Malware.k (v)", "TrendMicro": null, "McAfee-GW-Edition": "BehavesLike.Downloader.tb", "FireEye": null, "Emsisoft": null, "Ikarus": null, "Cyren": null, "Jiangmin": "MSWord/Downloader.az", "MAX": null, "Antiy-AVL": null, "Kingsoft": null, "Endgame": "malicious (high confidence)", "Microsoft": "Trojan:O97M/Sonbokli.A!cl", "SUPERAntiSpyware": null, "ZoneAlarm": null, "Avast-Mobile": null, "GData": null, "AhnLab-V3": null, "McAfee": null, "TACHYON": null, "VBA32": null, "Zoner": "W97ShellA", "Rising": "Macro.Downloader.r (CLASSIC)", "Yandex": null, "SentinelOne": "DFI - Malicious OLE", "Fortinet": null, "BitDefenderTheta": null, "AVG": null, "Panda": null, "Qihoo-360": "heur.macro.download.y"}
