{"Bkav": null, "MicroWorld-eScan": null, "CMC": null, "CAT-QuickHeal": null, "McAfee": null, "Malwarebytes": null, "Zillya": null, "SUPERAntiSpyware": null, "Sangfor": "Malware", "K7AntiVirus": null, "K7GW": null, "Arcabit": "HEUR.VBA.Trojan.e", "BitDefenderTheta": null, "F-Prot": null, "Symantec": null, "TotalDefense": null, "Baidu": "VBA.Trojan-Downloader.Agent.dvv", "TrendMicro-HouseCall": null, "Avast": "VBA:Downloader-EWW [Trj]", "ClamAV": null, "Kaspersky": null, "BitDefender": null, "NANO-Antivirus": null, "ViRobot": null, "Tencent": "Heur.MSWord.Downloader.d", "Ad-Aware": null, "Emsisoft": null, "Comodo": null, "F-Secure": null, "DrWeb": null, "VIPRE": null, "TrendMicro": null, "McAfee-GW-Edition": null, "Fortinet": null, "FireEye": null, "Sophos": null, "SentinelOne": "DFI - Malicious OLE", "Cyren": null, "Jiangmin": null, "Avira": null, "MAX": null, "Kingsoft": null, "Endgame": null, "Microsoft": null, "AegisLab": null, "ZoneAlarm": null, "Avast-Mobile": null, "AhnLab-V3": null, "VBA32": null, "ALYac": null, "TACHYON": "Suspicious/X97M.Obfus.Gen.1", "Zoner": null, "ESET-NOD32": null, "Rising": "Heur.Macro.Downloader.g (CLASSIC)", "Yandex": null, "Ikarus": null, "GData": "Macro.Trojan-Downloader.Agent.HT", "AVG": "VBA:Downloader-EWW [Trj]", "Panda": null, "Qihoo-360": null}
