{"Bkav": null, "MicroWorld-eScan": "W97m.Downloader.ISW", "CMC": null, "CAT-QuickHeal": null, "McAfee": null, "Malwarebytes": null, "Zillya": null, "SUPERAntiSpyware": null, "Sangfor": null, "K7AntiVirus": null, "K7GW": null, "Arcabit": "W97m.Downloader.ISW", "Baidu": null, "F-Prot": "W97M/Vba.gen", "Symantec": null, "ESET-NOD32": "VBA/TrojanDropper.Agent.ARC", "TrendMicro-HouseCall": "TROJ_FRS.VSNTLI19", "Avast": null, "ClamAV": null, "Kaspersky": "HEUR:Trojan-Dropper.MSOffice.SDrop.gen", "BitDefender": "W97m.Downloader.ISW", "NANO-Antivirus": "Trojan.Ole2.Vbs-heuristic.druvzi", "AegisLab": null, "Tencent": null, "Endgame": "malicious (high confidence)", "Sophos": null, "Comodo": null, "F-Secure": "Malware.W97M/Agent.39307166", "DrWeb": "Exploit.Siggen.50949", "VIPRE": null, "TrendMicro": "TROJ_FRS.VSNTLI19", "McAfee-GW-Edition": "BehavesLike.Downloader.gg", "FireEye": "W97m.Downloader.ISW", "Emsisoft": "W97m.Downloader.ISW (B)", "SentinelOne": "DFI - Malicious OLE", "Cyren": "W97M/Vba.gen", "Jiangmin": null, "Avira": "W97M/Agent.39307166", "Antiy-AVL": null, "Kingsoft": null, "Microsoft": "TrojanDropper:O97M/Powdow.AM!MTB", "ViRobot": null, "ZoneAlarm": "HEUR:Trojan-Dropper.MSOffice.SDrop.gen", "Avast-Mobile": null, "GData": "W97m.Downloader.ISW", "TACHYON": null, "AhnLab-V3": null, "VBA32": null, "ALYac": null, "MAX": "malware (ai score=84)", "Ad-Aware": "W97m.Downloader.ISW", "Zoner": "Probably W97Obfuscated", "Rising": "Dropper.Agent!8.2F (TOPIS:E0:3uyLXbgSLPU)", "Yandex": null, "Ikarus": null, "Fortinet": "VBA/Agent.ARC!tr", "BitDefenderTheta": null, "AVG": null, "Panda": null, "Qihoo-360": "virus.office.obfuscated.1"}
