{"Bkav": null, "DrWeb": "modification of W97M.Suspicious.1", "MicroWorld-eScan": "VB.PwShell.2.Gen", "FireEye": "VB.PwShell.2.Gen", "CAT-QuickHeal": null, "McAfee": null, "Malwarebytes": null, "Zillya": null, "SUPERAntiSpyware": null, "Sangfor": null, "K7AntiVirus": null, "K7GW": null, "BitDefenderTheta": null, "F-Prot": null, "Symantec": null, "TotalDefense": null, "TrendMicro-HouseCall": null, "Avast": "VBA:Downloader-EQF [Trj]", "ClamAV": null, "Kaspersky": null, "BitDefender": "VB.PwShell.2.Gen", "NANO-Antivirus": "Trojan.Ole2.Vbs-heuristic.druvzi", "ViRobot": null, "Tencent": "Heur.Macro.Generic.Gen.a", "Endgame": "malicious (moderate confidence)", "Sophos": null, "Comodo": null, "F-Secure": null, "Baidu": "VBA.Trojan-Downloader.Agent.brq", "VIPRE": null, "TrendMicro": null, "McAfee-GW-Edition": "BehavesLike.Downloader.lx", "CMC": null, "Emsisoft": "VB.PwShell.2.Gen (B)", "SentinelOne": "DFI - Malicious OLE", "Cyren": null, "Jiangmin": null, "Avira": null, "Fortinet": null, "Antiy-AVL": null, "Kingsoft": null, "Arcabit": "VB.PwShell.2.Gen", "AegisLab": null, "ZoneAlarm": "HEUR:Trojan-Downloader.Script.Generic", "Avast-Mobile": null, "Microsoft": null, "TACHYON": null, "AhnLab-V3": null, "VBA32": null, "ALYac": "VB.PwShell.2.Gen", "MAX": "malware (ai score=89)", "Ad-Aware": "VB.PwShell.2.Gen", "Zoner": "Probably W97Shell", "ESET-NOD32": null, "Rising": null, "Yandex": null, "Ikarus": null, "MaxSecure": null, "GData": "VB.PwShell.2.Gen", "AVG": "VBA:Downloader-EQF [Trj]", "Panda": null, "Qihoo-360": "heur.macro.powershell.3"}
