{"Bkav": null, "TotalDefense": null, "MicroWorld-eScan": "VB:Trojan.VBA.Agent.AYI", "FireEye": "VB:Trojan.VBA.Agent.AYI", "CAT-QuickHeal": "W97M.Emotet.36349", "ALYac": "VB:Trojan.VBA.Agent.AYI", "Malwarebytes": null, "Zillya": null, "SUPERAntiSpyware": null, "Sangfor": null, "K7AntiVirus": null, "K7GW": null, "Arcabit": "VB:Trojan.VBA.Agent.AYI", "BitDefenderTheta": null, "F-Prot": "New or modified W97M/Downldr", "Symantec": "W97M.Downloader", "ESET-NOD32": "VBA/TrojanDownloader.Agent.QPK", "Baidu": null, "TrendMicro-HouseCall": "Troj_Gen.F04IE00KQ19", "Avast": "Script:SNH-gen [Trj]", "ClamAV": "Doc.Downloader.Emotet-7431033-0", "Kaspersky": "HEUR:Trojan.MSOffice.SAgent.gen", "BitDefender": "VB:Trojan.VBA.Agent.AYI", "NANO-Antivirus": null, "AegisLab": null, "Tencent": "Heur.Macro.Generic.Gen.h", "Ad-Aware": "VB:Trojan.VBA.Agent.AYI", "Sophos": "Mal/DocDl-K", "Comodo": "Malware@#3jr4fvh76m262", "F-Secure": "Trojan:W97M/AutorunMacro.C", "DrWeb": "Exploit.Siggen.48303", "VIPRE": null, "TrendMicro": "Troj_Gen.F04IE00KQ19", "McAfee-GW-Edition": "BehavesLike.Downloader.dg", "CMC": null, "Emsisoft": "VB:Trojan.VBA.Agent.AYI (B)", "SentinelOne": "DFI - Suspicious OLE", "Cyren": "W97M/Downldr", "Jiangmin": null, "Avira": "W97M/Agent.396871099", "Antiy-AVL": "Trojan[Downloader]/MSOffice.Agent.cl", "Kingsoft": null, "Endgame": "malicious (high confidence)", "Microsoft": "TrojanDownloader:O97M/Emotet.RQ!MTB", "ViRobot": null, "ZoneAlarm": "HEUR:Trojan.MSOffice.SAgent.gen", "Avast-Mobile": null, "GData": "VB:Trojan.VBA.Agent.AYI", "TACHYON": null, "AhnLab-V3": "VBA/Downloader.S66", "McAfee": "W97M/Downloader.xx", "MAX": "malware (ai score=89)", "VBA32": null, "Zoner": "Probably W97Obfuscated", "Rising": null, "Yandex": null, "Ikarus": "Trojan-Downloader.VBA.Emotet", "MaxSecure": null, "Fortinet": "VBA/Agent.MUV!tr.dldr", "AVG": "Script:SNH-gen [Trj]", "Panda": null, "Qihoo-360": "virus.office.obfuscated.1"}
