{"Bkav": null, "MicroWorld-eScan": null, "CMC": null, "CAT-QuickHeal": "X97M.Agent.34591", "McAfee": "X97M/Laroux.f", "Malwarebytes": null, "Zillya": null, "Sangfor": null, "K7AntiVirus": null, "K7GW": null, "BitDefenderTheta": null, "Cyren": null, "ESET-NOD32": "X97M/Escoper.N", "Baidu": "VBA.Trojan.Agent.el", "TrendMicro-HouseCall": null, "Avast": null, "ClamAV": "Xls.Malware.Valyria-6744613-0", "Kaspersky": null, "BitDefender": null, "NANO-Antivirus": "Trojan.Script.Agent.fkbqor", "ViRobot": null, "AegisLab": null, "Tencent": "OLE.Win32.Macro.704118", "Endgame": "malicious (high confidence)", "Sophos": null, "Comodo": null, "F-Secure": "Heuristic.HEUR/Macro.Downloader.PWA.Gen", "DrWeb": "MACRO.Virus", "VIPRE": null, "TrendMicro": null, "McAfee-GW-Edition": "BehavesLike.Laroux.mr", "FireEye": null, "Emsisoft": null, "Ikarus": null, "F-Prot": null, "Jiangmin": null, "Avira": "HEUR/Macro.Downloader.PWA.Gen", "Antiy-AVL": null, "Kingsoft": null, "Microsoft": "Virus:X97M/Laroux.A", "Arcabit": null, "SUPERAntiSpyware": null, "ZoneAlarm": null, "Avast-Mobile": null, "GData": null, "TACHYON": null, "AhnLab-V3": null, "VBA32": null, "ALYac": null, "MAX": null, "Ad-Aware": null, "Zoner": null, "Rising": "Virus.Laroux!8.A15 (TOPIS:E0:A8VwGAzWruO)", "Yandex": null, "SentinelOne": "DFI - Malicious OLE", "MaxSecure": null, "Fortinet": "VBA/Escop.N", "AVG": null, "Panda": null, "Qihoo-360": "macro.excel.vir.2p"}
