{"Bkav": null, "TotalDefense": null, "MicroWorld-eScan": "VBA.Manilla.2.Gen", "VBA32": null, "FireEye": "VBA.Manilla.2.Gen", "CAT-QuickHeal": null, "ALYac": "VBA.Manilla.2.Gen", "Malwarebytes": null, "VIPRE": null, "SUPERAntiSpyware": null, "Sangfor": null, "K7AntiVirus": null, "K7GW": null, "Arcabit": "VBA.Manilla.2.Gen", "Baidu": null, "F-Prot": null, "Symantec": null, "ESET-NOD32": null, "TrendMicro-HouseCall": null, "Avast": null, "ClamAV": null, "Kaspersky": null, "BitDefender": "VBA.Manilla.2.Gen", "NANO-Antivirus": null, "ViRobot": null, "Tencent": null, "Endgame": null, "Sophos": null, "Comodo": null, "F-Secure": null, "DrWeb": null, "Zillya": null, "TrendMicro": null, "McAfee-GW-Edition": null, "CMC": null, "Emsisoft": "VBA.Manilla.2.Gen (B)", "SentinelOne": null, "Cyren": null, "Jiangmin": null, "Avira": null, "Fortinet": null, "Antiy-AVL": null, "Kingsoft": null, "Microsoft": null, "AegisLab": null, "ZoneAlarm": null, "Avast-Mobile": null, "TACHYON": null, "AhnLab-V3": null, "McAfee": null, "MAX": "malware (ai score=85)", "Ad-Aware": "VBA.Manilla.2.Gen", "Zoner": null, "Rising": null, "Yandex": null, "Ikarus": null, "GData": "VBA.Manilla.2.Gen", "AVG": null, "Panda": null, "Qihoo-360": null}
